setup.cfg
setup.py
optityper_to_sqlite/__init__.py
optityper_to_sqlite/__main__.py
optityper_to_sqlite/main.py
optityper_to_sqlite.egg-info/PKG-INFO
optityper_to_sqlite.egg-info/SOURCES.txt
optityper_to_sqlite.egg-info/dependency_links.txt
optityper_to_sqlite.egg-info/entry_points.txt
optityper_to_sqlite.egg-info/requires.txt
optityper_to_sqlite.egg-info/top_level.txt
optityper_to_sqlite/metrics/__init__.py
optityper_to_sqlite/metrics/optityper_result.py